{
  "generatedAt": "2026-07-08T03:57:55.980Z",
  "lighthouseVersion": "12.8.2",
  "testedUrl": "https://safal207.github.io/robys-coffee-house-demo/?audit=32a27af28a8831d702c3c4ff947232f6e11ea97f",
  "commit": "32a27af28a8831d702c3c4ff947232f6e11ea97f",
  "build": "20260626-8",
  "mobile": {
    "categories": {
      "performance": 62,
      "accessibility": 100,
      "best-practices": 100,
      "seo": 100
    },
    "metrics": {
      "first-contentful-paint": {
        "displayValue": "1.5 s",
        "numericValue": 1451.281
      },
      "largest-contentful-paint": {
        "displayValue": "3.1 s",
        "numericValue": 3067.281
      },
      "speed-index": {
        "displayValue": "5.1 s",
        "numericValue": 5125.214867159352
      },
      "total-blocking-time": {
        "displayValue": "2,110 ms",
        "numericValue": 2114
      },
      "cumulative-layout-shift": {
        "displayValue": "0",
        "numericValue": 0
      },
      "interactive": {
        "displayValue": "4.5 s",
        "numericValue": 4486.731
      }
    },
    "opportunities": [
      {
        "id": "render-blocking-resources",
        "title": "Eliminate render-blocking resources",
        "displayValue": "Est savings of 300 ms",
        "score": 0
      },
      {
        "id": "server-response-time",
        "title": "Initial server response time was short",
        "displayValue": "Root document took 10 ms",
        "score": 1
      }
    ]
  },
  "desktop": {
    "categories": {
      "performance": 100,
      "accessibility": 100,
      "best-practices": 78,
      "seo": 100
    },
    "metrics": {
      "first-contentful-paint": {
        "displayValue": "0.3 s",
        "numericValue": 255.85399999999998
      },
      "largest-contentful-paint": {
        "displayValue": "0.4 s",
        "numericValue": 373.854
      },
      "speed-index": {
        "displayValue": "0.5 s",
        "numericValue": 518.2554833774292
      },
      "total-blocking-time": {
        "displayValue": "0 ms",
        "numericValue": 0
      },
      "cumulative-layout-shift": {
        "displayValue": "0",
        "numericValue": 0
      },
      "interactive": {
        "displayValue": "0.4 s",
        "numericValue": 377.154
      }
    },
    "opportunities": [
      {
        "id": "server-response-time",
        "title": "Initial server response time was short",
        "displayValue": "Root document took 0 ms",
        "score": 1
      }
    ]
  }
}
