{
  "generatedAt": "2026-06-22T11:38:38.205Z",
  "lighthouseVersion": "12.8.2",
  "testedUrl": "https://safal207.github.io/robys-coffee-house-demo/?audit=8eecc0e459447f738742acbe9474d743ad94b7e6",
  "commit": "8eecc0e459447f738742acbe9474d743ad94b7e6",
  "build": "20260622-22",
  "mobile": {
    "categories": {
      "performance": 61,
      "accessibility": 100,
      "best-practices": 100,
      "seo": 100
    },
    "metrics": {
      "first-contentful-paint": {
        "displayValue": "3.7 s",
        "numericValue": 3650.188
      },
      "largest-contentful-paint": {
        "displayValue": "5.3 s",
        "numericValue": 5294.7675
      },
      "speed-index": {
        "displayValue": "5.1 s",
        "numericValue": 5091.940586802399
      },
      "total-blocking-time": {
        "displayValue": "360 ms",
        "numericValue": 356
      },
      "cumulative-layout-shift": {
        "displayValue": "0",
        "numericValue": 0
      },
      "interactive": {
        "displayValue": "5.3 s",
        "numericValue": 5294.7675
      }
    },
    "opportunities": [
      {
        "id": "uses-rel-preconnect",
        "title": "Preconnect to required origins",
        "displayValue": "Est savings of 310 ms",
        "score": 0
      },
      {
        "id": "server-response-time",
        "title": "Initial server response time was short",
        "displayValue": "Root document took 10 ms",
        "score": 1
      }
    ]
  },
  "desktop": {
    "categories": {
      "performance": 100,
      "accessibility": 100,
      "best-practices": 100,
      "seo": 100
    },
    "metrics": {
      "first-contentful-paint": {
        "displayValue": "0.4 s",
        "numericValue": 433.714
      },
      "largest-contentful-paint": {
        "displayValue": "0.4 s",
        "numericValue": 433.714
      },
      "speed-index": {
        "displayValue": "0.5 s",
        "numericValue": 513.0052874166645
      },
      "total-blocking-time": {
        "displayValue": "0 ms",
        "numericValue": 0
      },
      "cumulative-layout-shift": {
        "displayValue": "0",
        "numericValue": 0
      },
      "interactive": {
        "displayValue": "0.4 s",
        "numericValue": 433.714
      }
    },
    "opportunities": [
      {
        "id": "server-response-time",
        "title": "Initial server response time was short",
        "displayValue": "Root document took 0 ms",
        "score": 1
      }
    ]
  }
}
