{
  "generatedAt": "2026-06-23T23:54:32.000Z",
  "lighthouseVersion": "12.8.2",
  "testedUrl": "https://safal207.github.io/robys-coffee-house-demo/?audit=6d6c6980c7da0e2f1b8bf6f8a500252ac0b5ce76",
  "commit": "6d6c6980c7da0e2f1b8bf6f8a500252ac0b5ce76",
  "build": "20260624-1",
  "mobile": {
    "categories": {
      "performance": 73,
      "accessibility": 95,
      "best-practices": 100,
      "seo": 100
    },
    "metrics": {
      "first-contentful-paint": {
        "displayValue": "1.8 s",
        "numericValue": 1829.58
      },
      "largest-contentful-paint": {
        "displayValue": "2.2 s",
        "numericValue": 2166.58
      },
      "speed-index": {
        "displayValue": "3.1 s",
        "numericValue": 3060.700147609338
      },
      "total-blocking-time": {
        "displayValue": "1,250 ms",
        "numericValue": 1249
      },
      "cumulative-layout-shift": {
        "displayValue": "0",
        "numericValue": 0
      },
      "interactive": {
        "displayValue": "3.5 s",
        "numericValue": 3539.08
      }
    },
    "opportunities": [
      {
        "id": "server-response-time",
        "title": "Initial server response time was short",
        "displayValue": "Root document took 100 ms",
        "score": 1
      }
    ]
  },
  "desktop": {
    "categories": {
      "performance": 100,
      "accessibility": 95,
      "best-practices": 93,
      "seo": 100
    },
    "metrics": {
      "first-contentful-paint": {
        "displayValue": "0.4 s",
        "numericValue": 435.241
      },
      "largest-contentful-paint": {
        "displayValue": "0.4 s",
        "numericValue": 448.741
      },
      "speed-index": {
        "displayValue": "0.5 s",
        "numericValue": 543.5012095834954
      },
      "total-blocking-time": {
        "displayValue": "0 ms",
        "numericValue": 0
      },
      "cumulative-layout-shift": {
        "displayValue": "0",
        "numericValue": 0
      },
      "interactive": {
        "displayValue": "0.5 s",
        "numericValue": 450.091
      }
    },
    "opportunities": [
      {
        "id": "server-response-time",
        "title": "Initial server response time was short",
        "displayValue": "Root document took 0 ms",
        "score": 1
      }
    ]
  }
}
