{
  "generatedAt": "2026-06-21T05:30:27.124Z",
  "lighthouseVersion": "12.8.2",
  "testedUrl": "http://127.0.0.1:8080/",
  "device": {
    "formFactor": "mobile",
    "screenEmulation": {
      "mobile": true,
      "width": 412,
      "height": 823,
      "deviceScaleFactor": 1.75,
      "disabled": false
    },
    "throttlingMethod": "simulate",
    "throttling": {
      "rttMs": 150,
      "throughputKbps": 1638.4,
      "requestLatencyMs": 562.5,
      "downloadThroughputKbps": 1474.5600000000002,
      "uploadThroughputKbps": 675,
      "cpuSlowdownMultiplier": 4
    },
    "locale": "en-US"
  },
  "categories": {
    "performance": 69,
    "accessibility": 100,
    "best-practices": 100,
    "seo": 100
  },
  "metrics": {
    "first-contentful-paint": {
      "displayValue": "1.9 s",
      "numericValue": 1871.1879,
      "score": 0.88
    },
    "largest-contentful-paint": {
      "displayValue": "2.5 s",
      "numericValue": 2484.0788249999996,
      "score": 0.9
    },
    "speed-index": {
      "displayValue": "3.3 s",
      "numericValue": 3302.904316478662,
      "score": 0.91
    },
    "total-blocking-time": {
      "displayValue": "1,600 ms",
      "numericValue": 1604.4060500000005,
      "score": 0.12
    },
    "cumulative-layout-shift": {
      "displayValue": "0",
      "numericValue": 0,
      "score": 1
    },
    "interactive": {
      "displayValue": "4.1 s",
      "numericValue": 4084.29395,
      "score": 0.87
    }
  },
  "opportunities": [
    {
      "id": "uses-text-compression",
      "title": "Enable text compression",
      "displayValue": "Est savings of 59 KiB",
      "score": 0
    },
    {
      "id": "modern-image-formats",
      "title": "Serve images in next-gen formats",
      "displayValue": "Est savings of 13 KiB",
      "score": 0
    },
    {
      "id": "render-blocking-resources",
      "title": "Eliminate render-blocking resources",
      "displayValue": "Est savings of 0 ms",
      "score": 0.5
    }
  ],
  "failedAudits": [
    {
      "id": "mainthread-work-breakdown",
      "title": "Minimize main-thread work",
      "score": 0,
      "displayValue": "4.4 s"
    },
    {
      "id": "modern-image-formats",
      "title": "Serve images in next-gen formats",
      "score": 0,
      "displayValue": "Est savings of 13 KiB"
    },
    {
      "id": "uses-text-compression",
      "title": "Enable text compression",
      "score": 0,
      "displayValue": "Est savings of 59 KiB"
    },
    {
      "id": "cache-insight",
      "title": "Use efficient cache lifetimes",
      "score": 0,
      "displayValue": "Est savings of 213 KiB"
    },
    {
      "id": "image-delivery-insight",
      "title": "Improve image delivery",
      "score": 0,
      "displayValue": "Est savings of 11 KiB"
    },
    {
      "id": "network-dependency-tree-insight",
      "title": "Network dependency tree",
      "score": 0,
      "displayValue": null
    },
    {
      "id": "max-potential-fid",
      "title": "Max Potential First Input Delay",
      "score": 0.04,
      "displayValue": "610 ms"
    },
    {
      "id": "total-blocking-time",
      "title": "Total Blocking Time",
      "score": 0.12,
      "displayValue": "1,600 ms"
    },
    {
      "id": "uses-long-cache-ttl",
      "title": "Serve static assets with an efficient cache policy",
      "score": 0.5,
      "displayValue": "19 resources found"
    },
    {
      "id": "render-blocking-resources",
      "title": "Eliminate render-blocking resources",
      "score": 0.5,
      "displayValue": "Est savings of 0 ms"
    },
    {
      "id": "document-latency-insight",
      "title": "Document request latency",
      "score": 0.5,
      "displayValue": "Est savings of 9 KiB"
    },
    {
      "id": "render-blocking-insight",
      "title": "Render blocking requests",
      "score": 0.5,
      "displayValue": null
    },
    {
      "id": "interactive",
      "title": "Time to Interactive",
      "score": 0.87,
      "displayValue": "4.1 s"
    },
    {
      "id": "first-contentful-paint",
      "title": "First Contentful Paint",
      "score": 0.88,
      "displayValue": "1.9 s"
    }
  ]
}
